llama_index/tools/hive/__init__.py
llama_index/tools/hive/base.py
llama_index_tools_hive-0.2.1.dist-info/METADATA
llama_index_tools_hive-0.2.1.dist-info/WHEEL
llama_index_tools_hive-0.2.1.dist-info/RECORD
