Metadata-Version: 2.4
Name: llama-index-tools-hive
Version: 0.2.1
Summary: LlamaIndex Tool for Hive Intelligence
License: MIT
Classifier: License :: OSI Approved :: MIT License
Classifier: Operating System :: OS Independent
Classifier: Programming Language :: Python :: 3
Requires-Python: >=3.9
Requires-Dist: hive-intelligence>=0.1.0
Requires-Dist: llama-index-core<0.15,>=0.13.0
Provides-Extra: dev
Requires-Dist: black>=23.0.0; extra == 'dev'
Requires-Dist: isort>=5.0.0; extra == 'dev'
Requires-Dist: mypy>=1.0.0; extra == 'dev'
Requires-Dist: pytest-cov>=3.0.0; extra == 'dev'
Requires-Dist: pytest>=6.0; extra == 'dev'
Provides-Extra: test
Requires-Dist: pytest-cov>=3.0.0; extra == 'test'
Requires-Dist: pytest>=6.0; extra == 'test'
